catprompt/__init__.py
catprompt/prompter.py
catprompt-0.2.0.dist-info/LICENSE
catprompt-0.2.0.dist-info/METADATA
catprompt-0.2.0.dist-info/WHEEL
catprompt-0.2.0.dist-info/entry_points.txt
catprompt-0.2.0.dist-info/top_level.txt
catprompt-0.2.0.dist-info/RECORD
