Metadata-Version: 2.1
Name: catprompt
Version: 0.2.0
Summary: Combine prompts for chatgpt.
Author-email: Juan Reyero <juan@juanreyero.com>
License: Copyright (c) 2018 The Python Packaging Authority
Classifier: Programming Language :: Python :: 3
Classifier: License :: OSI Approved :: MIT License
Classifier: Operating System :: OS Independent
Requires-Python: >=3.8
License-File: LICENSE
Requires-Dist: clipboard
Requires-Dist: tiktoken
Provides-Extra: dev
Requires-Dist: jedi (>=0.18.1) ; extra == 'dev'
Requires-Dist: pylint (>=2.13.9) ; extra == 'dev'
Requires-Dist: pytest (>=7.0.0) ; extra == 'dev'
Requires-Dist: yapf (>=0.32.0) ; extra == 'dev'
Requires-Dist: build ; extra == 'dev'
Requires-Dist: twine ; extra == 'dev'
